ecgpy/__init__.py
ecgpy-0.1.0.dist-info/METADATA
ecgpy-0.1.0.dist-info/WHEEL
ecgpy-0.1.0.dist-info/RECORD
