Metadata-Version: 2.1
Name: ecgpy
Version: 0.1.0
Summary: 
Author: YAJIE
Author-email: yajiez.me@gmail.com
Requires-Python: >=3.11,<4.0
Classifier: Programming Language :: Python :: 3
Classifier: Programming Language :: Python :: 3.11
Classifier: Programming Language :: Python :: 3.12
Requires-Dist: numpy (>=2.3.0,<3.0.0)
Requires-Dist: pandas (>=2.3.0,<3.0.0)
Requires-Dist: scikit-learn (>=1.7.0,<2.0.0)
Requires-Dist: seaborn (>=0.13.2,<0.14.0)
Requires-Dist: statsmodels (>=0.14.4,<0.15.0)
Requires-Dist: torch (>=2.7.1,<3.0.0)
